phish/__init__.py
phish/api.py
phish-0.1.dist-info/DESCRIPTION.rst
phish-0.1.dist-info/LICENSE.txt
phish-0.1.dist-info/METADATA
phish-0.1.dist-info/RECORD
phish-0.1.dist-info/WHEEL
phish-0.1.dist-info/metadata.json
phish-0.1.dist-info/top_level.txt
